{"libgcc-ng-9.4.0-h4229099_0.tar.bz2": {"mtime": 1679527460, "size": 2171}, "libgcc-ng-8.2.0-h6c28c44_0.tar.bz2": {"mtime": 1679527449, "size": 2163}, "libgcc-ng-7.5.0-he3b9f8c_0.tar.bz2": {"mtime": 1679527470, "size": 2176}, "libgcc-ng-11.2.0-hd2d1e73_0.tar.bz2": {"mtime": 1679527440, "size": 2174}, "libgcc-ng-9.1.0-h80a7923_0.tar.bz2": {"mtime": 1679527442, "size": 2170}, "libgcc-ng-5.4.0-he2f48ca_0.tar.bz2": {"mtime": 1679527438, "size": 2168}, "libgcc-ng-11.3.0-he32a10e_0.tar.bz2": {"mtime": 1679527462, "size": 2178}, "libgcc-ng-7.2.0-hc289f0a_0.tar.bz2": {"mtime": 1679527478, "size": 2178}, "libgcc-ng-7.3.0-hf2a5326_0.tar.bz2": {"mtime": 1679527452, "size": 2170}, "libgcc-ng-8.4.0-h6610ba0_0.tar.bz2": {"mtime": 1679527445, "size": 2167}, "libgcc-ng-9.2.0-h8706c53_0.tar.bz2": {"mtime": 1679527468, "size": 2181}, "libgcc-ng-12.1.0-h9aeeb40_0.tar.bz2": {"mtime": 1679527457, "size": 2163}, "libgcc-ng-9.3.0-hd908cf2_0.tar.bz2": {"mtime": 1679527483, "size": 2178}, "libgcc-ng-10.3.0-h6c89060_0.tar.bz2": {"mtime": 1679527481, "size": 2167}, "libgcc-ng-8.5.0-ha8a7394_0.tar.bz2": {"mtime": 1679527475, "size": 2172}, "libgcc-ng-9.5.0-hff5d94d_0.tar.bz2": {"mtime": 1679527454, "size": 2173}, "libgcc-ng-11.1.0-h141590a_0.tar.bz2": {"mtime": 1679527465, "size": 2167}, "libgcc-ng-12.2.0-hbf4f601_0.tar.bz2": {"mtime": 1679527473, "size": 2172}, "libgcc-ng-10.4.0-h57d9167_0.tar.bz2": {"mtime": 1679527447, "size": 2169}}