{"libgomp-11.3.0-he32a10e_0.tar.bz2": {"mtime": 1680129940, "size": 2314}, "libgomp-10.3.0-h6c89060_0.tar.bz2": {"mtime": 1680129928, "size": 2316}, "libgomp-7.3.0-hf2a5326_0.tar.bz2": {"mtime": 1680129961, "size": 2310}, "libgomp-8.5.0-ha8a7394_0.tar.bz2": {"mtime": 1680129930, "size": 2321}, "libgomp-11.1.0-h141590a_0.tar.bz2": {"mtime": 1680129952, "size": 2325}, "libgomp-9.4.0-h4229099_0.tar.bz2": {"mtime": 1680129933, "size": 2323}, "libgomp-8.4.0-h6610ba0_0.tar.bz2": {"mtime": 1680129935, "size": 2316}, "libgomp-12.2.0-hbf4f601_0.tar.bz2": {"mtime": 1680129942, "size": 2323}, "libgomp-9.2.0-h8706c53_0.tar.bz2": {"mtime": 1680129937, "size": 2309}, "libgomp-9.5.0-hff5d94d_0.tar.bz2": {"mtime": 1680129954, "size": 2329}, "libgomp-7.5.0-he3b9f8c_0.tar.bz2": {"mtime": 1680129945, "size": 2316}, "libgomp-10.4.0-h57d9167_0.tar.bz2": {"mtime": 1680129947, "size": 2319}, "libgomp-12.1.0-h9aeeb40_0.tar.bz2": {"mtime": 1680129959, "size": 2323}, "libgomp-11.2.0-hd2d1e73_0.tar.bz2": {"mtime": 1680129957, "size": 2318}, "libgomp-9.3.0-hd908cf2_0.tar.bz2": {"mtime": 1680129949, "size": 2324}}